pylgnetcast/__init__.py
pylgnetcast/__main__.py
pylgnetcast/pylgnetcast.py
pylgnetcast-0.3.8.dist-info/LICENSE
pylgnetcast-0.3.8.dist-info/METADATA
pylgnetcast-0.3.8.dist-info/WHEEL
pylgnetcast-0.3.8.dist-info/top_level.txt
pylgnetcast-0.3.8.dist-info/RECORD
