Metadata-Version: 2.1
Name: pylgnetcast
Version: 0.3.8
Summary: Client for the LG Smart TV running NetCast 3 or 4.
Home-page: https://github.com/Drafteed/python-lgnetcast
Maintainer: Artem Draft
Maintainer-email: artemon_93@mail.ru
License: MIT
Classifier: Programming Language :: Python :: 3
Classifier: License :: OSI Approved :: MIT License
Classifier: Operating System :: OS Independent
Requires-Python: >=3.6
License-File: LICENSE
Requires-Dist: requests
